{
  "todos": [
    {
      "id": "d49c89bd-69dc-42ce-a855-8d8a0cee0d6e",
      "text": "asdfdsafasfsda emir",
      "completed": false
    },
    {
      "id": "191b6487-11a2-4c45-8d84-8ac7d6e468a8",
      "text": "asdfadsf",
      "completed": false
    },
    {
      "id": "4a39b1df-5310-4ef8-b19c-44ae9c470c12",
      "text": "jangan",
      "completed": false
    },
    {
      "id": "6359c344-1832-44ff-b237-9c4609e62281",
      "text": "asfdasdf",
      "completed": false
    },
    {
      "id": "e54445f9-5890-4574-a751-2a4059b47553",
      "text": "asdfasdfa asdfasdf",
      "completed": false
    },
    {
      "id": "c3fe26f8-7614-4ff0-9d63-efa3ba2edd10",
      "text": "SASDADSDSA",
      "completed": false
    }
  ]
}